supervisor_core.cpython-312-x86_64-linux-gnu.so
simulator/__init__.py
simulator/python/__init__.py
simulator/python/base_simulator.py
simulator/python/base_simulator_test.py
simulator/python/gpu_failure_simulator.py
simulator/python/gpu_failure_simulator_test.py
simulator/python/gpu_slowdown_simulator.py
simulator/python/gpu_slowdown_simulator_test.py
simulator/python/xid_simulator.py
simulator/python/xid_simulator_test.py
supervisor/__init__.py
supervisor/client/__init__.py
supervisor/client/python/__init__.py
supervisor/client/python/actuator.py
supervisor/client/python/actuator_test.py
supervisor/client/python/controller.py
supervisor/client/python/controller_test.py
supervisor/client/python/host.py
supervisor/client/python/host_test.py
supervisor/client/python/sensor.py
supervisor/client/python/sensor_test.py
supervisor/client/python/utils.py
supervisor/client/python/utils_test.py
supervisor/client/python/workload.py
supervisor/client/python/workload_test.py
supervisor/client/python/orchestrators/__init__.py
supervisor/client/python/orchestrators/gke_callbacks.py
supervisor/client/python/orchestrators/gke_callbacks_test.py
supervisor/client/python/test/__init__.py
supervisor/client/python/test/constants.py
supervisor/client/python/test/test_utils.py
supervisor/core/__init__.py
supervisor/core/python/__init__.py
supervisor/core/python/device_info.py
supervisor/core/python/device_info_test.py
supervisor/core/python/setup.py
supervisor/core/python/utils.py
supervisor/core/python/utils_test.py
supervisor/watchdogs/__init__.py
supervisor/watchdogs/python/__init__.py
supervisor/watchdogs/python/base_watchdog.py
supervisor/watchdogs/python/base_watchdog_test.py
supervisor/watchdogs/python/ecc_watchdog.py
supervisor/watchdogs/python/ecc_watchdog_test.py
supervisor/watchdogs/python/xid_watchdog.py
supervisor/watchdogs/python/xid_watchdog_test.py
google_cloud_resiliency_supervisor-1.0.5.dist-info/METADATA
google_cloud_resiliency_supervisor-1.0.5.dist-info/WHEEL
google_cloud_resiliency_supervisor-1.0.5.dist-info/top_level.txt
google_cloud_resiliency_supervisor-1.0.5.dist-info/RECORD
