Metadata-Version: 2.4
Name: google-cloud-resiliency-supervisor
Version: 1.0.5
Summary: Google Cloud Resiliency Supervisor
Author: Google Cloud
Author-email: catmint-eng@google.com
Classifier: Programming Language :: Python :: 3
Classifier: Operating System :: OS Independent
Requires-Python: >=3.8
Dynamic: author
Dynamic: author-email
Dynamic: classifier
Dynamic: requires-python
Dynamic: summary
